unit_system/__init__.py
unit_system/predefined_units.py
unit_system/quantity.py
unit_system/version.py
unit_system-1.1.7.dist-info/LICENSE
unit_system-1.1.7.dist-info/METADATA
unit_system-1.1.7.dist-info/WHEEL
unit_system-1.1.7.dist-info/top_level.txt
unit_system-1.1.7.dist-info/RECORD
