Metadata-Version: 2.1
Name: unit-system
Version: 1.1.7
Summary: SI unit system implementation enabling physical quantity math
Home-page: https://github.com/l-johnston/unit_system
Author: Lee Johnston
Author-email: lee.johnston.100@gmail.com
License: MIT
Platform: UNKNOWN
Classifier: Programming Language :: Python :: 3
Classifier: Topic :: Scientific/Engineering
Classifier: License :: OSI Approved :: MIT License
Classifier: Intended Audience :: Science/Research
Requires-Dist: numpy (>=1.17.0)
Requires-Dist: sympy (>=1.4)
Requires-Dist: unyt (>=2.6.0)
